niftypet/__init__.py
niftypet/ninst/__init__.py
niftypet/ninst/_dist_ver.py
niftypet/ninst/cudasetup.py
niftypet/ninst/dinf.py
niftypet/ninst/install_tools.py
niftypet/ninst/tools.py
niftypet/ninst/raw/__init__.py
niftypet/ninst/raw/resources.py
ninst-0.12.0.dist-info/LICENCE
ninst-0.12.0.dist-info/METADATA
ninst-0.12.0.dist-info/WHEEL
ninst-0.12.0.dist-info/top_level.txt
ninst-0.12.0.dist-info/RECORD
